ucam_faas/__init__.py
ucam_faas/_logging.py
ucam_faas/cloud_events.py
ucam_faas/contexts.py
ucam_faas/contextual_handlers.py
ucam_faas/exceptions.py
ucam_faas/execution_info.py
ucam_faas/gcp_pubsub.py
ucam_faas/handler_execution.py
ucam_faas/loading.py
ucam_faas/messages.py
ucam_faas/py.typed
ucam_faas/pydantic.py
ucam_faas/testing.py
ucam_faas/tests/__init__.py
ucam_faas/tests/conftest.py
ucam_faas/tests/fixtures.py
ucam_faas/tests/not_a_module.txt
ucam_faas/tests/protobuf/example.proto
ucam_faas/tests/protobuf/example_pb2.py
ucam_faas/tests/protobuf/example_pb2.pyi
ucam_faas/tests/test_cloud_events.py
ucam_faas/tests/test_contexts.py
ucam_faas/tests/test_contextual_handlers.py
ucam_faas/tests/test_exceptions.py
ucam_faas/tests/test_execution_info.py
ucam_faas/tests/test_gcp_pubsub.py
ucam_faas/tests/test_handler_execution.py
ucam_faas/tests/test_input_file.py
ucam_faas/tests/test_loading.py
ucam_faas/tests/test_messages.py
ucam_faas/tests/test_pydantic.py
ucam_faas/tests/test_testing.py
ucam_faas/tests/test_ucam_faas.py
ucam_faas-0.21.0.dist-info/METADATA
ucam_faas-0.21.0.dist-info/WHEEL
ucam_faas-0.21.0.dist-info/entry_points.txt
ucam_faas-0.21.0.dist-info/RECORD
